README.rst
setup.py
mr/__init__.py
mr.cython.egg-info/PKG-INFO
mr.cython.egg-info/SOURCES.txt
mr.cython.egg-info/dependency_links.txt
mr.cython.egg-info/entry_points.txt
mr.cython.egg-info/namespace_packages.txt
mr.cython.egg-info/not-zip-safe
mr.cython.egg-info/requires.txt
mr.cython.egg-info/top_level.txt
mr/cython/__init__.py