Metadata-Version: 1.1
Name: mr.cython
Version: 1.0
Summary: A zc.buildout extension to befriend mr.developer and Cython.
Home-page: http://github.com/sendgridlabs/mr.cython
Author: Alexander V. Nikolaev
Author-email: avn@daemon.hole.ru
License: BSD
Platform: UNKNOWN
Classifier: Programming Language :: Python
Classifier: Framework :: Buildout
Classifier: Topic :: Software Development :: Libraries :: Python Modules
